fastapi_paseto/__init__.py
fastapi_paseto/auth_config.py
fastapi_paseto/auth_paseto.py
fastapi_paseto/config.py
fastapi_paseto/exceptions.py
fastapi_paseto-0.7.1.dist-info/LICENSE
fastapi_paseto-0.7.1.dist-info/WHEEL
fastapi_paseto-0.7.1.dist-info/METADATA
fastapi_paseto-0.7.1.dist-info/RECORD
