Metadata-Version: 2.1
Name: fastapi_paseto
Version: 0.7.1
Summary: FastAPI extension that provides PASETO Auth support
Author-email: Neneko <fastapi@nyu.moe>
Classifier: License :: OSI Approved :: MIT License
Project-URL: Home, https://github.com/yashram96/fastapi-paseto
